skywise_insight-1.0.4.dist-info/DESCRIPTION.rst
skywise_insight-1.0.4.dist-info/METADATA
skywise_insight-1.0.4.dist-info/metadata.json
skywise_insight-1.0.4.dist-info/RECORD
skywise_insight-1.0.4.dist-info/top_level.txt
skywise_insight-1.0.4.dist-info/WHEEL
skywiseinsight/__init__.py
skywiseinsight/_daily_resource.py
skywiseinsight/_degree_days_resource.py
skywiseinsight/_hourly_resource.py
skywiseinsight/asset.py
skywiseinsight/cdd.py
skywiseinsight/daily_et_short_crop.py
skywiseinsight/daily_et_tall_crop.py
skywiseinsight/daily_high_temperature.py
skywiseinsight/daily_low_temperature.py
skywiseinsight/daily_precipitation.py
skywiseinsight/daily_solar_radiation.py
skywiseinsight/gdd.py
skywiseinsight/hdd.py
skywiseinsight/hourly_dewpoint.py
skywiseinsight/hourly_et_short_crop.py
skywiseinsight/hourly_et_tall_crop.py
skywiseinsight/hourly_precipitation.py
skywiseinsight/hourly_relative_humidity.py
skywiseinsight/hourly_solar_radiation.py
skywiseinsight/hourly_temperature.py
skywiseinsight/hourly_wind_direction.py
skywiseinsight/hourly_wind_speed.py
